README.rst
setup.py
sklearn2vantage/__init__.py
sklearn2vantage/dataloader.py
sklearn2vantage/modelchanger.py
sklearn2vantage.egg-info/PKG-INFO
sklearn2vantage.egg-info/SOURCES.txt
sklearn2vantage.egg-info/dependency_links.txt
sklearn2vantage.egg-info/requires.txt
sklearn2vantage.egg-info/top_level.txt