Metadata-Version: 1.1
Name: sklearn2vantage
Version: 0.1.6
Summary: Module for converting sklearn model to Teradata Vantage model
Home-page: https://github.com/Yukimura66/sklearn2vantage
Author: Akihiro Sanada
Author-email: akihiro.sanada@icloud.com
License: MIT
Keywords: Teradata scikit-learn Vantage
Platform: UNKNOWN
Classifier: Topic :: Database
Classifier: Programming Language :: Python :: 3 :: Only
Classifier: License :: OSI Approved :: MIT License
Classifier: Topic :: Scientific/Engineering :: Artificial Intelligence
